df_compress/__init__.py
df_compress/df_compress.py
df_compress-0.7.0.dist-info/licenses/LICENSE
df_compress-0.7.0.dist-info/METADATA
df_compress-0.7.0.dist-info/WHEEL
df_compress-0.7.0.dist-info/top_level.txt
df_compress-0.7.0.dist-info/RECORD
